flask_gripcontrol.py
setup.cfg
setup.py
Flask_GripControl.egg-info/PKG-INFO
Flask_GripControl.egg-info/SOURCES.txt
Flask_GripControl.egg-info/dependency_links.txt
Flask_GripControl.egg-info/requires.txt
Flask_GripControl.egg-info/top_level.txt